dynaport/__init__.py
dynaport/dynaport.py
dynaport-0.0.16.dist-info/LICENSE
dynaport-0.0.16.dist-info/METADATA
dynaport-0.0.16.dist-info/WHEEL
dynaport-0.0.16.dist-info/top_level.txt
dynaport-0.0.16.dist-info/RECORD
