Metadata-Version: 2.1
Name: dynaport
Version: 0.0.16
Summary: dynamic module importer
Home-page: https://github.com/naek2k/dynaport
Author: naek
Author-email: naek2k@outlook.com
License: UNKNOWN
Platform: UNKNOWN
Classifier: Programming Language :: Python
Classifier: License :: OSI Approved :: Apache Software License
Classifier: Operating System :: OS Independent
Requires-Python: >=2
